wikibaseintegrator/__init__.py
wikibaseintegrator/datatypes/__init__.py
wikibaseintegrator/datatypes/basedatatype.py
wikibaseintegrator/datatypes/commonsmedia.py
wikibaseintegrator/datatypes/entityschema.py
wikibaseintegrator/datatypes/externalid.py
wikibaseintegrator/datatypes/extra/__init__.py
wikibaseintegrator/datatypes/extra/edtf.py
wikibaseintegrator/datatypes/extra/localmedia.py
wikibaseintegrator/datatypes/form.py
wikibaseintegrator/datatypes/geoshape.py
wikibaseintegrator/datatypes/globecoordinate.py
wikibaseintegrator/datatypes/item.py
wikibaseintegrator/datatypes/lexeme.py
wikibaseintegrator/datatypes/math.py
wikibaseintegrator/datatypes/monolingualtext.py
wikibaseintegrator/datatypes/musicalnotation.py
wikibaseintegrator/datatypes/property.py
wikibaseintegrator/datatypes/quantity.py
wikibaseintegrator/datatypes/sense.py
wikibaseintegrator/datatypes/string.py
wikibaseintegrator/datatypes/tabulardata.py
wikibaseintegrator/datatypes/time.py
wikibaseintegrator/datatypes/url.py
wikibaseintegrator/entities/__init__.py
wikibaseintegrator/entities/baseentity.py
wikibaseintegrator/entities/item.py
wikibaseintegrator/entities/lexeme.py
wikibaseintegrator/entities/mediainfo.py
wikibaseintegrator/entities/property.py
wikibaseintegrator/models/__init__.py
wikibaseintegrator/models/aliases.py
wikibaseintegrator/models/basemodel.py
wikibaseintegrator/models/claims.py
wikibaseintegrator/models/descriptions.py
wikibaseintegrator/models/forms.py
wikibaseintegrator/models/labels.py
wikibaseintegrator/models/language_values.py
wikibaseintegrator/models/lemmas.py
wikibaseintegrator/models/qualifiers.py
wikibaseintegrator/models/references.py
wikibaseintegrator/models/senses.py
wikibaseintegrator/models/sitelinks.py
wikibaseintegrator/models/snaks.py
wikibaseintegrator/wbi_backoff.py
wikibaseintegrator/wbi_config.py
wikibaseintegrator/wbi_enums.py
wikibaseintegrator/wbi_exceptions.py
wikibaseintegrator/wbi_fastrun.py
wikibaseintegrator/wbi_helpers.py
wikibaseintegrator-0.12.15.dist-info/METADATA
wikibaseintegrator-0.12.15.dist-info/WHEEL
wikibaseintegrator-0.12.15.dist-info/licenses/LICENSE
wikibaseintegrator-0.12.15.dist-info/RECORD
