Metadata-Version: 2.4
Name: WikibaseIntegrator
Version: 0.12.15
Summary: Python package for reading from and writing to a Wikibase instance
License: MIT
License-File: LICENSE
Keywords: wikibase,wikidata,mediawiki,sparql
Author: Myst
Requires-Python: >=3.9,<4.0
Classifier: Development Status :: 4 - Beta
Classifier: Intended Audience :: Developers
Classifier: Intended Audience :: Information Technology
Classifier: Intended Audience :: Science/Research
Classifier: License :: OSI Approved :: MIT License
Classifier: Operating System :: MacOS :: MacOS X
Classifier: Operating System :: Microsoft :: Windows
Classifier: Operating System :: POSIX
Classifier: Programming Language :: Python
Classifier: Programming Language :: Python :: 3
Classifier: Programming Language :: Python :: 3.9
Classifier: Programming Language :: Python :: 3.10
Classifier: Programming Language :: Python :: 3.11
Classifier: Programming Language :: Python :: 3.12
Classifier: Programming Language :: Python :: 3.13
Classifier: Programming Language :: Python :: 3.14
Classifier: Topic :: Software Development :: Libraries :: Python Modules
Classifier: Topic :: Utilities
Requires-Dist: backoff (>=2.2.1,<3.0.0)
Requires-Dist: mwoauth (>=0.4.0,<0.5.0)
Requires-Dist: oauthlib (>=3.2.2,<4.0.0)
Requires-Dist: requests (>=2.32.3,<3.0.0)
Requires-Dist: requests-oauthlib (>=2.0.0,<3.0.0)
Requires-Dist: ujson (>=5.10.0,<6.0.0)
Project-URL: Bug Tracker, https://github.com/LeMyst/WikibaseIntegrator/issues
Project-URL: Changelog, https://github.com/LeMyst/WikibaseIntegrator/releases
Project-URL: Documentation, https://wikibaseintegrator.readthedocs.io
Project-URL: Homepage, https://github.com/LeMyst/WikibaseIntegrator
Project-URL: Repository, https://github.com/LeMyst/WikibaseIntegrator
